examples/spcs_example.py
spcs_kinematics/__init__.py
spcs_kinematics/jax_math/__init__.py
spcs_kinematics/jax_math/jax_cs.py
spcs_kinematics/jax_math/jax_jacobian.py
spcs_kinematics/jax_math/jax_lie_algebra.py
spcs_kinematics/jax_math/jax_linear_algebra.py
spcs_kinematics/jax_math/jax_pcs.py
spcs_kinematics/jax_math/jax_pose_error.py
spcs_kinematics/jax_math/jax_quaternion.py
spcs_kinematics/jax_math/jax_rod_mesh.py
spcs_kinematics/jax_math/jax_rotation.py
spcs_kinematics/jax_math/jax_spcs.py
spcs_kinematics/kinematic_parametrizations/__init__.py
spcs_kinematics/kinematic_parametrizations/base_kinematic_parametrization.py
spcs_kinematics/kinematic_parametrizations/cc_cf.py
spcs_kinematics/kinematic_parametrizations/cs.py
spcs_kinematics/kinematic_parametrizations/numeric_kinematics.py
spcs_kinematics/kinematic_parametrizations/spcs.py
spcs_kinematics/visualization/__init__.py
spcs_kinematics/visualization/plot_inverse_kinematics_convergence.py
spcs_kinematics/visualization/plot_rod_shape.py
tests/test_cc_kinematics.py
jax_spcs_kinematics-0.0.1.dist-info/LICENSE
jax_spcs_kinematics-0.0.1.dist-info/METADATA
jax_spcs_kinematics-0.0.1.dist-info/WHEEL
jax_spcs_kinematics-0.0.1.dist-info/top_level.txt
jax_spcs_kinematics-0.0.1.dist-info/RECORD
