Metadata-Version: 2.1
Name: jax-spcs-kinematics
Version: 0.0.1
Summary: Implements the Selective Piecewise Constant Strain (SPCS) approach to model the kinematics of continuum soft robots.
Author-email: Maximilian Stölzle <maximilian@stoelzle.ch>
License: MIT
Classifier: Development Status :: 3 - Alpha
Classifier: Intended Audience :: Developers
Classifier: Topic :: Software Development :: Build Tools
Classifier: License :: OSI Approved :: MIT License
Classifier: Programming Language :: Python :: 3
Classifier: Programming Language :: Python :: 3.10
Classifier: Programming Language :: Python :: 3 :: Only
Requires-Python: >=3.8
License-File: LICENSE
Requires-Dist: dill
Requires-Dist: jax
Requires-Dist: matplotlib
Requires-Dist: numpy
Requires-Dist: progressbar2
Provides-Extra: dev
Requires-Dist: black ; extra == 'dev'
Requires-Dist: bump2version ; extra == 'dev'
Requires-Dist: codecov ; extra == 'dev'
Requires-Dist: coverage ; extra == 'dev'
Requires-Dist: pre-commit ; extra == 'dev'
Requires-Dist: pytest ; extra == 'dev'
Requires-Dist: pytest-cov ; extra == 'dev'
Requires-Dist: pytest-html ; extra == 'dev'
Requires-Dist: tox ; extra == 'dev'
